setup.py
bbking/__init__.py
bbking/admin.py
bbking/fields.py
bbking/lexer.py
bbking/models.py
bbking/parser.py
bbking/test_settings.py
bbking.egg-info/PKG-INFO
bbking.egg-info/SOURCES.txt
bbking.egg-info/dependency_links.txt
bbking.egg-info/requires.txt
bbking.egg-info/top_level.txt
bbking/bbtags/__init__.py
bbking/bbtags/code.py
bbking/bbtags/embed.py
bbking/bbtags/hrefs.py
bbking/bbtags/quote.py
bbking/bbtags/text.py
bbking/migrations/0001_initial.py
bbking/migrations/__init__.py
bbking/templates/bbking/tags/b.html
bbking/templates/bbking/tags/code.html
bbking/templates/bbking/tags/embed.html
bbking/templates/bbking/tags/i.html
bbking/templates/bbking/tags/img.html
bbking/templates/bbking/tags/quote.html
bbking/templates/bbking/tags/strike.html
bbking/templates/bbking/tags/u.html
bbking/templates/bbking/tags/url.html
bbking/templates/bbking/tags/youtube.html
bbking/templatetags/__init__.py
bbking/templatetags/bbking.py
bbking/templatetags/wordfilter.py
bbking/tests/__init__.py
bbking/tests/fields.py
bbking/tests/parser.py