Metadata-Version: 1.0
Name: bbking
Version: 0.0.1
Summary: A Django BBCode Parser
Home-page: UNKNOWN
Author: Rev. Johnny Healey
Author-email: rev.null@gmail.com
License: GPL3
Platform: UNKNOWN
